{
    "model_name_or_path": "/home/liuyh0916/models/open_models/llama-2-7b-chat-hf",
    "method": "token",
    "dataset": "strategyqa",
    "data_path": "datasets/strategyqa",
    "fewshot": 6,
    "sample": 1000,
    "shuffle": false,
    "generate_max_length": 100,
    "query_formulation": "forward_all",
    "output_dir": "results/llama2_7b_chat_strategyqa",
    "retriever": "BM25",
    "es_index_name": "wiki",
    "retrieve_topk": 3,
    "hallucination_threshold": 0.1,
    "use_counter": true
}